ansible/module_utils/network/radware/__init__.py
ansible/module_utils/network/radware/alteon.py
ansible/module_utils/network/radware/common.py
ansible/module_utils/network/radware/configuration.py
ansible/module_utils/network/radware/management.py
ansible/modules/network/radware/__init__.py
ansible/modules/network/radware/alteon_config_appshape.py
ansible/modules/network/radware/alteon_config_dns_responders.py
ansible/modules/network/radware/alteon_config_fqdn_server.py
ansible/modules/network/radware/alteon_config_global_redirection.py
ansible/modules/network/radware/alteon_config_gslb_network.py
ansible/modules/network/radware/alteon_config_gslb_rule.py
ansible/modules/network/radware/alteon_config_ha_config_sync.py
ansible/modules/network/radware/alteon_config_ha_floating_ip.py
ansible/modules/network/radware/alteon_config_health_check_http.py
ansible/modules/network/radware/alteon_config_health_check_logexp.py
ansible/modules/network/radware/alteon_config_health_check_tcp.py
ansible/modules/network/radware/alteon_config_high_availability.py
ansible/modules/network/radware/alteon_config_l2_lldp.py
ansible/modules/network/radware/alteon_config_l2_vlan.py
ansible/modules/network/radware/alteon_config_l3_bootp_relay.py
ansible/modules/network/radware/alteon_config_l3_gateway.py
ansible/modules/network/radware/alteon_config_l3_interface.py
ansible/modules/network/radware/alteon_config_lacp_aggregation.py
ansible/modules/network/radware/alteon_config_network_class_ip.py
ansible/modules/network/radware/alteon_config_network_class_region.py
ansible/modules/network/radware/alteon_config_physical_port.py
ansible/modules/network/radware/alteon_config_server.py
ansible/modules/network/radware/alteon_config_server_group.py
ansible/modules/network/radware/alteon_config_slb_pip.py
ansible/modules/network/radware/alteon_config_spanning_tree.py
ansible/modules/network/radware/alteon_config_ssl_cert.py
ansible/modules/network/radware/alteon_config_ssl_cert_group.py
radware_ansible_common_alteon-0.3b35.dist-info/COPYING
radware_ansible_common_alteon-0.3b35.dist-info/METADATA
radware_ansible_common_alteon-0.3b35.dist-info/WHEEL
radware_ansible_common_alteon-0.3b35.dist-info/top_level.txt
radware_ansible_common_alteon-0.3b35.dist-info/RECORD
