Metadata-Version: 2.1
Name: radware-ansible-common-alteon
Version: 0.3b35
Summary: Radware Common and Alteon Modules for Ansible
Home-page: https://pypi.python.org/pypi/radware-ansible-common-alteon
Author: Leon Meguira
Author-email: leonm@radware.com
License: GPLv3+
Keywords: radware,ansible,alteon,common
Platform: UNKNOWN
Classifier: Development Status :: 4 - Beta
Classifier: License :: OSI Approved :: GNU General Public License v3 or later (GPLv3+)
Classifier: Operating System :: OS Independent
Classifier: Programming Language :: Python :: 3.6
Classifier: Programming Language :: Python :: 3.7
Classifier: Programming Language :: Python :: 3.8
Classifier: Intended Audience :: System Administrators
Classifier: Intended Audience :: Developers
Requires-Python: ~=3.6
Requires-Dist: ansible (>=2.7.0)
Requires-Dist: future
